MANIFEST.in
README.txt
setup.py
docs/HISTORY.txt
silvatheme/__init__.py
silvatheme.multiflex.egg-info/PKG-INFO
silvatheme.multiflex.egg-info/SOURCES.txt
silvatheme.multiflex.egg-info/dependency_links.txt
silvatheme.multiflex.egg-info/namespace_packages.txt
silvatheme.multiflex.egg-info/not-zip-safe
silvatheme.multiflex.egg-info/requires.txt
silvatheme.multiflex.egg-info/top_level.txt
silvatheme/multiflex/__init__.py
silvatheme/multiflex/configure.zcml
silvatheme/multiflex/multiflex.py
silvatheme/multiflex/multiflex_templates/layout.pt
silvatheme/multiflex/static/bg_bullet_arrow.gif
silvatheme/multiflex/static/bg_bullet_full_1.gif
silvatheme/multiflex/static/bg_bullet_full_2.gif
silvatheme/multiflex/static/bg_bullet_half_1.gif
silvatheme/multiflex/static/bg_bullet_half_2.gif
silvatheme/multiflex/static/bg_corner_topleft.gif
silvatheme/multiflex/static/bg_corner_topright.gif
silvatheme/multiflex/static/bg_foot.jpg
silvatheme/multiflex/static/bg_head_bottom_nav.jpg
silvatheme/multiflex/static/bg_head_breadcrumbs.jpg
silvatheme/multiflex/static/bg_head_middle.jpg
silvatheme/multiflex/static/bg_head_top.jpg
silvatheme/multiflex/static/bg_head_top_logo.jpg
silvatheme/multiflex/static/bg_main_withnav.jpg
silvatheme/multiflex/static/bg_main_withnav_reverse.jpg
silvatheme/multiflex/static/bg_main_withoutnav.jpg
silvatheme/multiflex/static/favicon.ico
silvatheme/multiflex/static/image.jpg
silvatheme/multiflex/static/layout_setup.css
silvatheme/multiflex/static/layout_text.css
silvatheme/multiflex/static/myphoto.jpg