Metadata-Version: 1.1
Name: silvatheme.multiflex
Version: 1.0
Summary: Multiflex Demo Skin for Silva CMS
Home-page: https://github.com/silvacms/silvatheme.multiflex
Author: Wim Boucquaert
Author-email: info@infrae.com
License: BSD
Keywords: skin silva
Platform: UNKNOWN
Classifier: Programming Language :: Python
Classifier: Topic :: Software Development :: Libraries :: Python Modules
